{"DateTime":"2016-01-06T00:00:00","Players":2,"TimeGlobal":0,"KillsGlobal":0,"GemsGlobal":0,"DeathsGlobal":0,"DaggersHitGlobal":0,"DaggersFiredGlobal":0,"Entries":[{"Rank":1,"Id":1,"Username":"m4ttbush","Time":2953886,"Kills":497,"Gems":144,"DeathType":2,"DaggersHit":1631,"DaggersFired":10000,"TimeTotal":0,"KillsTotal":0,"GemsTotal":0,"DeathsTotal":0,"DaggersHitTotal":0,"DaggersFiredTotal":0},{"Rank":2,"Id":6,"Username":"Boneman","Time":1764840,"Kills":0,"Gems":0,"DeathType":-1,"DaggersHit":0,"DaggersFired":0,"TimeTotal":0,"KillsTotal":0,"GemsTotal":0,"DeathsTotal":0,"DaggersHitTotal":0,"DaggersFiredTotal":0}]}