{"DateTime":"2020-01-09T00:00:12.5788548Z","Players":208783,"TimeGlobal":14204732306009,"KillsGlobal":3358890501,"GemsGlobal":443418582,"DeathsGlobal":19414059,"ShotsHitGlobal":7189054376,"ShotsFiredGlobal":32065111782,"Entries":[{"Rank":1,"ID":148788,"Username":"Bintr","Time":11143351,"Kills":4313,"Gems":1743,"DeathType":7,"ShotsHit":35640,"ShotsFired":93390,"TimeTotal":46619204334,"KillsTotal":14025682,"GemsTotal":4238028,"DeathsTotal":93571,"ShotsHitTotal":79296721,"ShotsFiredTotal":243416996},{"Rank":2,"ID":229,"Username":"Olof","Time":11129805,"Kills":4902,"Gems":1793,"DeathType":10,"ShotsHit":35874,"ShotsFired":94572,"TimeTotal":25039958762,"KillsTotal":9053713,"GemsTotal":2755823,"DeathsTotal":6814,"ShotsHitTotal":51733187,"ShotsFiredTotal":153858048},{"Rank":3,"ID":116704,"Username":"m4tt you fucking nlgger","Time":11090170,"Kills":4292,"Gems":1720,"DeathType":3,"ShotsHit":34998,"ShotsFired":91207,"TimeTotal":11906466128,"KillsTotal":4291280,"GemsTotal":1234933,"DeathsTotal":3789,"ShotsHitTotal":22999554,"ShotsFiredTotal":68169285},{"Rank":4,"ID":118832,"Username":"Chupacabra","Time":11078129,"Kills":4111,"Gems":1655,"DeathType":5,"ShotsHit":34733,"ShotsFired":92124,"TimeTotal":20330042692,"KillsTotal":6370398,"GemsTotal":2084855,"DeathsTotal":6097,"ShotsHitTotal":40555079,"ShotsFiredTotal":122246059},{"Rank":5,"ID":106722,"Username":"pocket","Time":11056890,"Kills":4201,"Gems":1682,"DeathType":15,"ShotsHit":35214,"ShotsFired":92555,"TimeTotal":22393569769,"KillsTotal":7211436,"GemsTotal":1889777,"DeathsTotal":10645,"ShotsHitTotal":32711319,"ShotsFiredTotal":102363545},{"Rank":6,"ID":1545,"Username":"KrosisOne","Time":11055385,"Kills":4064,"Gems":1610,"DeathType":12,"ShotsHit":34844,"ShotsFired":95511,"TimeTotal":54348492960,"KillsTotal":16649270,"GemsTotal":5233512,"DeathsTotal":17056,"ShotsHitTotal":98055019,"ShotsFiredTotal":308417820},{"Rank":7,"ID":93991,"Username":"cookle","Time":10983640,"Kills":4243,"Gems":1699,"DeathType":1,"ShotsHit":34005,"ShotsFired":93123,"TimeTotal":17729654158,"KillsTotal":5071333,"GemsTotal":1530076,"DeathsTotal":9627,"ShotsHitTotal":26607397,"ShotsFiredTotal":83613871},{"Rank":8,"ID":86805,"Username":"Ravenholmzombies","Time":10951364,"Kills":3985,"Gems":1659,"DeathType":10,"ShotsHit":34169,"ShotsFired":95637,"TimeTotal":19921201447,"KillsTotal":5748004,"GemsTotal":1745898,"DeathsTotal":6940,"ShotsHitTotal":31317251,"ShotsFiredTotal":110036350},{"Rank":9,"ID":1135,"Username":"bowsr","Time":10803359,"Kills":4099,"Gems":1602,"DeathType":5,"ShotsHit":33341,"ShotsFired":88113,"TimeTotal":15760336525,"KillsTotal":5410939,"GemsTotal":1623269,"DeathsTotal":5106,"ShotsHitTotal":29746918,"ShotsFiredTotal":85650923},{"Rank":10,"ID":134802,"Username":"gLad","Time":10797339,"Kills":4049,"Gems":1628,"DeathType":1,"ShotsHit":33442,"ShotsFired":91476,"TimeTotal":22736018730,"KillsTotal":7235780,"GemsTotal":2086453,"DeathsTotal":7800,"ShotsHitTotal":37490689,"ShotsFiredTotal":119362422},{"Rank":11,"ID":6760,"Username":"TSTAB","Time":10758875,"Kills":3870,"Gems":1463,"DeathType":11,"ShotsHit":32940,"ShotsFired":90680,"TimeTotal":22617862102,"KillsTotal":6787079,"GemsTotal":1807527,"DeathsTotal":9547,"ShotsHitTotal":31265991,"ShotsFiredTotal":105345369},{"Rank":12,"ID":1677,"Username":"ᴧ и т.⁴","Time":10735461,"Kills":3992,"Gems":1475,"DeathType":5,"ShotsHit":31801,"ShotsFired":87803,"TimeTotal":16309516001,"KillsTotal":5328582,"GemsTotal":1578291,"DeathsTotal":4808,"ShotsHitTotal":29475652,"ShotsFiredTotal":91372626},{"Rank":13,"ID":182924,"Username":"axe","Time":10698502,"Kills":3628,"Gems":1437,"DeathType":6,"ShotsHit":32682,"ShotsFired":99549,"TimeTotal":14161691786,"KillsTotal":4078630,"GemsTotal":1079926,"DeathsTotal":6669,"ShotsHitTotal":19505162,"ShotsFiredTotal":68604604},{"Rank":14,"ID":21854,"Username":"xvlv","Time":10630103,"Kills":3801,"Gems":1446,"DeathType":7,"ShotsHit":31233,"ShotsFired":86913,"TimeTotal":20227718895,"KillsTotal":5464737,"GemsTotal":1914845,"DeathsTotal":5570,"ShotsHitTotal":37377543,"ShotsFiredTotal":124132255},{"Rank":15,"ID":173419,"Username":"Kasa","Time":10628096,"Kills":3533,"Gems":1474,"DeathType":5,"ShotsHit":32335,"ShotsFired":90458,"TimeTotal":10655812048,"KillsTotal":2958186,"GemsTotal":979954,"DeathsTotal":3441,"ShotsHitTotal":18579335,"ShotsFiredTotal":61072941},{"Rank":16,"ID":153452,"Username":"tacocat","Time":10584949,"Kills":3855,"Gems":1486,"DeathType":3,"ShotsHit":31539,"ShotsFired":91301,"TimeTotal":17785224187,"KillsTotal":5251441,"GemsTotal":1383258,"DeathsTotal":8946,"ShotsHitTotal":22964653,"ShotsFiredTotal":78977891},{"Rank":17,"ID":10210,"Username":"sjorsbw","Time":10398480,"Kills":3035,"Gems":1463,"DeathType":3,"ShotsHit":29478,"ShotsFired":86834,"TimeTotal":14872735603,"KillsTotal":3566923,"GemsTotal":1251103,"DeathsTotal":6981,"ShotsHitTotal":21662408,"ShotsFiredTotal":76828279},{"Rank":18,"ID":148130,"Username":"BLANK_END","Time":10391958,"Kills":3298,"Gems":1251,"DeathType":1,"ShotsHit":30684,"ShotsFired":89349,"TimeTotal":8036704061,"KillsTotal":2122241,"GemsTotal":593753,"DeathsTotal":3986,"ShotsHitTotal":11204372,"ShotsFiredTotal":38586390},{"Rank":19,"ID":105874,"Username":"Dkazyo","Time":10283254,"Kills":3266,"Gems":1449,"DeathType":10,"ShotsHit":29333,"ShotsFired":80296,"TimeTotal":11431180626,"KillsTotal":2994899,"GemsTotal":1007450,"DeathsTotal":4434,"ShotsHitTotal":17497188,"ShotsFiredTotal":58436435},{"Rank":20,"ID":5757,"Username":"Cobajj","Time":10274391,"Kills":3334,"Gems":1381,"DeathType":2,"ShotsHit":29430,"ShotsFired":83761,"TimeTotal":18128091522,"KillsTotal":4684262,"GemsTotal":1296396,"DeathsTotal":9661,"ShotsHitTotal":20219935,"ShotsFiredTotal":75444692},{"Rank":21,"ID":18469,"Username":"trauma queen","Time":10264189,"Kills":3402,"Gems":1304,"DeathType":1,"ShotsHit":29446,"ShotsFired":85429,"TimeTotal":8023144751,"KillsTotal":2303372,"GemsTotal":634745,"DeathsTotal":3597,"ShotsHitTotal":10686848,"ShotsFiredTotal":34269046},{"Rank":22,"ID":115431,"Username":"Pritster","Time":10258002,"Kills":2949,"Gems":1264,"DeathType":10,"ShotsHit":28571,"ShotsFired":91164,"TimeTotal":43534573121,"KillsTotal":10500612,"GemsTotal":3755486,"DeathsTotal":13264,"ShotsHitTotal":70078194,"ShotsFiredTotal":252837638},{"Rank":23,"ID":121891,"Username":"xamide","Time":10249473,"Kills":3328,"Gems":1338,"DeathType":1,"ShotsHit":29438,"ShotsFired":89015,"TimeTotal":10173406939,"KillsTotal":3086335,"GemsTotal":806573,"DeathsTotal":4642,"ShotsHitTotal":13606360,"ShotsFiredTotal":47356366},{"Rank":24,"ID":438,"Username":"Kaijt","Time":10179955,"Kills":2961,"Gems":1332,"DeathType":11,"ShotsHit":27866,"ShotsFired":80010,"TimeTotal":7456412450,"KillsTotal":2071737,"GemsTotal":647833,"DeathsTotal":2693,"ShotsHitTotal":10838142,"ShotsFiredTotal":35775751},{"Rank":25,"ID":10782,"Username":"Nullifier","Time":10179456,"Kills":3141,"Gems":1332,"DeathType":6,"ShotsHit":28757,"ShotsFired":92086,"TimeTotal":15824808495,"KillsTotal":4498207,"GemsTotal":1082579,"DeathsTotal":9153,"ShotsHitTotal":16877560,"ShotsFiredTotal":60063380},{"Rank":26,"ID":48687,"Username":"Hahmo","Time":10176290,"Kills":3483,"Gems":1398,"DeathType":1,"ShotsHit":28476,"ShotsFired":83350,"TimeTotal":12216021140,"KillsTotal":3228549,"GemsTotal":972891,"DeathsTotal":5174,"ShotsHitTotal":16458219,"ShotsFiredTotal":58044598},{"Rank":27,"ID":106181,"Username":"flubb","Time":10123136,"Kills":3285,"Gems":1313,"DeathType":11,"ShotsHit":27810,"ShotsFired":79796,"TimeTotal":14432891988,"KillsTotal":3724196,"GemsTotal":1025039,"DeathsTotal":9358,"ShotsHitTotal":16380113,"ShotsFiredTotal":55772030},{"Rank":28,"ID":188777,"Username":"_whipsta","Time":10119470,"Kills":3615,"Gems":1330,"DeathType":1,"ShotsHit":29291,"ShotsFired":91035,"TimeTotal":16646623992,"KillsTotal":5107598,"GemsTotal":1277990,"DeathsTotal":8284,"ShotsHitTotal":20600607,"ShotsFiredTotal":72351058},{"Rank":29,"ID":148518,"Username":"oi fuck head","Time":10112639,"Kills":2694,"Gems":1259,"DeathType":2,"ShotsHit":26830,"ShotsFired":84535,"TimeTotal":6499854913,"KillsTotal":1038891,"GemsTotal":347292,"DeathsTotal":60801,"ShotsHitTotal":6298490,"ShotsFiredTotal":21356139},{"Rank":30,"ID":65617,"Username":"pagedMov","Time":10106807,"Kills":2934,"Gems":1255,"DeathType":3,"ShotsHit":27867,"ShotsFired":89517,"TimeTotal":15022871312,"KillsTotal":3684148,"GemsTotal":1237916,"DeathsTotal":6556,"ShotsHitTotal":20859599,"ShotsFiredTotal":69365948},{"Rank":31,"ID":142939,"Username":"LocoCaesar_IV","Time":10100808,"Kills":3279,"Gems":1272,"DeathType":3,"ShotsHit":28364,"ShotsFired":87045,"TimeTotal":32489394425,"KillsTotal":8496037,"GemsTotal":2529290,"DeathsTotal":16869,"ShotsHitTotal":42816123,"ShotsFiredTotal":142112440},{"Rank":32,"ID":112710,"Username":"7stringTheory","Time":10038490,"Kills":2990,"Gems":1288,"DeathType":1,"ShotsHit":27207,"ShotsFired":85967,"TimeTotal":21963847552,"KillsTotal":6008646,"GemsTotal":1630156,"DeathsTotal":10135,"ShotsHitTotal":26806693,"ShotsFiredTotal":99515988},{"Rank":33,"ID":105641,"Username":"jay","Time":10029825,"Kills":3405,"Gems":1314,"DeathType":4,"ShotsHit":27752,"ShotsFired":85259,"TimeTotal":10029737059,"KillsTotal":3010170,"GemsTotal":722663,"DeathsTotal":6025,"ShotsHitTotal":11732494,"ShotsFiredTotal":38074998},{"Rank":34,"ID":184178,"Username":"Mizore <3","Time":9922852,"Kills":3051,"Gems":1255,"DeathType":1,"ShotsHit":27310,"ShotsFired":84561,"TimeTotal":1797687497,"KillsTotal":589545,"GemsTotal":152119,"DeathsTotal":778,"ShotsHitTotal":2671338,"ShotsFiredTotal":9259703},{"Rank":35,"ID":175805,"Username":"Enough","Time":9910521,"Kills":3316,"Gems":1254,"DeathType":1,"ShotsHit":27532,"ShotsFired":80131,"TimeTotal":7720877201,"KillsTotal":2229627,"GemsTotal":591427,"DeathsTotal":3845,"ShotsHitTotal":9601864,"ShotsFiredTotal":31600410},{"Rank":36,"ID":19658,"Username":"krak cant track~☆","Time":9864366,"Kills":2796,"Gems":1333,"DeathType":1,"ShotsHit":27579,"ShotsFired":80022,"TimeTotal":16237790671,"KillsTotal":4084647,"GemsTotal":1178891,"DeathsTotal":8260,"ShotsHitTotal":19173110,"ShotsFiredTotal":64769733},{"Rank":37,"ID":157181,"Username":"PS3 controller","Time":9837372,"Kills":3188,"Gems":1239,"DeathType":10,"ShotsHit":26816,"ShotsFired":83105,"TimeTotal":834477435,"KillsTotal":190476,"GemsTotal":52191,"DeathsTotal":314,"ShotsHitTotal":897858,"ShotsFiredTotal":3142588},{"Rank":38,"ID":2316,"Username":"aircawn","Time":9793883,"Kills":3034,"Gems":1212,"DeathType":10,"ShotsHit":25393,"ShotsFired":72143,"TimeTotal":14381961584,"KillsTotal":3894645,"GemsTotal":1246794,"DeathsTotal":4805,"ShotsHitTotal":21058959,"ShotsFiredTotal":67719531},{"Rank":39,"ID":90050,"Username":"Backdoor","Time":9688742,"Kills":3007,"Gems":1196,"DeathType":1,"ShotsHit":25529,"ShotsFired":77606,"TimeTotal":23850797921,"KillsTotal":6344793,"GemsTotal":1589175,"DeathsTotal":14675,"ShotsHitTotal":23905249,"ShotsFiredTotal":82583070},{"Rank":40,"ID":10045,"Username":"Blue53","Time":9578102,"Kills":2859,"Gems":1120,"DeathType":15,"ShotsHit":25290,"ShotsFired":74064,"TimeTotal":15292998597,"KillsTotal":4073516,"GemsTotal":1061600,"DeathsTotal":8229,"ShotsHitTotal":17441195,"ShotsFiredTotal":59450751},{"Rank":41,"ID":177725,"Username":"Deunousen","Time":9498455,"Kills":2957,"Gems":1126,"DeathType":1,"ShotsHit":25097,"ShotsFired":75552,"TimeTotal":5359628472,"KillsTotal":1509477,"GemsTotal":384177,"DeathsTotal":2482,"ShotsHitTotal":6080440,"ShotsFiredTotal":20986216},{"Rank":42,"ID":148538,"Username":"paxtank","Time":9484125,"Kills":2860,"Gems":1131,"DeathType":4,"ShotsHit":24613,"ShotsFired":75972,"TimeTotal":12741117004,"KillsTotal":3306247,"GemsTotal":806155,"DeathsTotal":9015,"ShotsHitTotal":12657976,"ShotsFiredTotal":43702145},{"Rank":43,"ID":81895,"Username":"zealotsthename † 狂热者","Time":9420974,"Kills":2677,"Gems":1096,"DeathType":6,"ShotsHit":23925,"ShotsFired":76689,"TimeTotal":13563873925,"KillsTotal":3445812,"GemsTotal":981793,"DeathsTotal":6980,"ShotsHitTotal":15663563,"ShotsFiredTotal":58769902},{"Rank":44,"ID":166973,"Username":"[G]rizz","Time":9397480,"Kills":2554,"Gems":1139,"DeathType":12,"ShotsHit":23792,"ShotsFired":75562,"TimeTotal":7964247941,"KillsTotal":2360345,"GemsTotal":522790,"DeathsTotal":4908,"ShotsHitTotal":8886341,"ShotsFiredTotal":33476200},{"Rank":45,"ID":152889,"Username":"Puhree","Time":9384816,"Kills":2534,"Gems":1167,"DeathType":10,"ShotsHit":23453,"ShotsFired":72024,"TimeTotal":12783945948,"KillsTotal":3390316,"GemsTotal":882279,"DeathsTotal":6562,"ShotsHitTotal":14345997,"ShotsFiredTotal":51583981},{"Rank":46,"ID":40892,"Username":"SheffieldWarrior","Time":9380817,"Kills":2650,"Gems":1118,"DeathType":15,"ShotsHit":24539,"ShotsFired":80238,"TimeTotal":9914302919,"KillsTotal":2138228,"GemsTotal":669270,"DeathsTotal":4632,"ShotsHitTotal":10967095,"ShotsFiredTotal":42678436},{"Rank":47,"ID":146931,"Username":"Duncdaddi","Time":9340494,"Kills":2539,"Gems":986,"DeathType":4,"ShotsHit":23646,"ShotsFired":71132,"TimeTotal":7543595798,"KillsTotal":1709206,"GemsTotal":478166,"DeathsTotal":4402,"ShotsHitTotal":7674894,"ShotsFiredTotal":29086477},{"Rank":48,"ID":105315,"Username":"LukeNukem","Time":9288840,"Kills":2821,"Gems":1049,"DeathType":12,"ShotsHit":23568,"ShotsFired":72729,"TimeTotal":22821753207,"KillsTotal":6976399,"GemsTotal":1461842,"DeathsTotal":14357,"ShotsHitTotal":22386406,"ShotsFiredTotal":76896303},{"Rank":49,"ID":75575,"Username":"pocket","Time":9257347,"Kills":2699,"Gems":1122,"DeathType":2,"ShotsHit":23493,"ShotsFired":67741,"TimeTotal":24972191869,"KillsTotal":6179794,"GemsTotal":2066803,"DeathsTotal":10643,"ShotsHitTotal":35403636,"ShotsFiredTotal":118598417},{"Rank":50,"ID":58654,"Username":"CCT","Time":9230021,"Kills":2492,"Gems":1010,"DeathType":11,"ShotsHit":22890,"ShotsFired":76845,"TimeTotal":10191285887,"KillsTotal":2651234,"GemsTotal":762364,"DeathsTotal":3793,"ShotsHitTotal":13742772,"ShotsFiredTotal":52371438},{"Rank":51,"ID":176615,"Username":"Hostolonius","Time":9228854,"Kills":2330,"Gems":984,"DeathType":10,"ShotsHit":23300,"ShotsFired":79489,"TimeTotal":9428882747,"KillsTotal":2082399,"GemsTotal":674060,"DeathsTotal":4759,"ShotsHitTotal":11618800,"ShotsFiredTotal":43913271},{"Rank":52,"ID":112879,"Username":"retardeder","Time":9176534,"Kills":3414,"Gems":1086,"DeathType":6,"ShotsHit":24407,"ShotsFired":79510,"TimeTotal":12701714951,"KillsTotal":4383554,"GemsTotal":753713,"DeathsTotal":11894,"ShotsHitTotal":11415020,"ShotsFiredTotal":38282597},{"Rank":53,"ID":82980,"Username":"Emberstone","Time":9172368,"Kills":2345,"Gems":1072,"DeathType":15,"ShotsHit":22147,"ShotsFired":63542,"TimeTotal":8678462457,"KillsTotal":2011118,"GemsTotal":614617,"DeathsTotal":4396,"ShotsHitTotal":9136795,"ShotsFiredTotal":31802873},{"Rank":54,"ID":166941,"Username":"iNooVa","Time":9149041,"Kills":2440,"Gems":889,"DeathType":3,"ShotsHit":23070,"ShotsFired":80412,"TimeTotal":2534836525,"KillsTotal":552681,"GemsTotal":163462,"DeathsTotal":1389,"ShotsHitTotal":2684117,"ShotsFiredTotal":10572713},{"Rank":55,"ID":4795,"Username":"Moz","Time":9129379,"Kills":2432,"Gems":1099,"DeathType":2,"ShotsHit":21908,"ShotsFired":68755,"TimeTotal":10249983289,"KillsTotal":2541187,"GemsTotal":854711,"DeathsTotal":3616,"ShotsHitTotal":13688635,"ShotsFiredTotal":49129693},{"Rank":56,"ID":94857,"Username":"Birder brain player","Time":9094720,"Kills":2231,"Gems":1061,"DeathType":3,"ShotsHit":22632,"ShotsFired":67990,"TimeTotal":4977881520,"KillsTotal":1091900,"GemsTotal":336329,"DeathsTotal":2597,"ShotsHitTotal":4846502,"ShotsFiredTotal":17623167},{"Rank":57,"ID":27510,"Username":"Billy the Butcher","Time":9058396,"Kills":2428,"Gems":986,"DeathType":3,"ShotsHit":21924,"ShotsFired":66412,"TimeTotal":8061114810,"KillsTotal":1900988,"GemsTotal":548829,"DeathsTotal":4573,"ShotsHitTotal":8534432,"ShotsFiredTotal":30008968},{"Rank":58,"ID":1029,"Username":"ohsnaplol","Time":9054897,"Kills":2419,"Gems":999,"DeathType":10,"ShotsHit":21331,"ShotsFired":64581,"TimeTotal":6238024601,"KillsTotal":1597295,"GemsTotal":445808,"DeathsTotal":2972,"ShotsHitTotal":7024766,"ShotsFiredTotal":24282277},{"Rank":59,"ID":157108,"Username":"Jyff","Time":9032736,"Kills":3091,"Gems":1090,"DeathType":1,"ShotsHit":23325,"ShotsFired":66953,"TimeTotal":22928879949,"KillsTotal":8074162,"GemsTotal":1562675,"DeathsTotal":13698,"ShotsHitTotal":25587405,"ShotsFiredTotal":87204131},{"Rank":60,"ID":193297,"Username":"Driftkon","Time":8998911,"Kills":2000,"Gems":811,"DeathType":5,"ShotsHit":21010,"ShotsFired":72885,"TimeTotal":5160120746,"KillsTotal":1056972,"GemsTotal":308000,"DeathsTotal":2691,"ShotsHitTotal":4628685,"ShotsFiredTotal":19111207},{"Rank":61,"ID":89987,"Username":"Goobermin","Time":8988913,"Kills":2693,"Gems":808,"DeathType":7,"ShotsHit":23010,"ShotsFired":79381,"TimeTotal":13638267219,"KillsTotal":4102768,"GemsTotal":803413,"DeathsTotal":9131,"ShotsHitTotal":13530084,"ShotsFiredTotal":47107537},{"Rank":62,"ID":71157,"Username":"Chopps The Penguin","Time":8935259,"Kills":2701,"Gems":995,"DeathType":11,"ShotsHit":22265,"ShotsFired":73096,"TimeTotal":8303778474,"KillsTotal":2328862,"GemsTotal":493012,"DeathsTotal":5574,"ShotsHitTotal":7832785,"ShotsFiredTotal":29006708},{"Rank":63,"ID":113530,"Username":"Zirtonic","Time":8924262,"Kills":2361,"Gems":992,"DeathType":2,"ShotsHit":22072,"ShotsFired":69751,"TimeTotal":4974650528,"KillsTotal":1137826,"GemsTotal":353860,"DeathsTotal":2203,"ShotsHitTotal":5374855,"ShotsFiredTotal":18710772},{"Rank":64,"ID":531,"Username":"GaryBanderas","Time":8924095,"Kills":2154,"Gems":1041,"DeathType":10,"ShotsHit":21362,"ShotsFired":64588,"TimeTotal":21307377146,"KillsTotal":4674808,"GemsTotal":1621924,"DeathsTotal":8447,"ShotsHitTotal":26273558,"ShotsFiredTotal":99948908},{"Rank":65,"ID":168681,"Username":"azuki","Time":8880606,"Kills":2261,"Gems":1029,"DeathType":3,"ShotsHit":21081,"ShotsFired":67661,"TimeTotal":6766319065,"KillsTotal":1852722,"GemsTotal":403218,"DeathsTotal":4538,"ShotsHitTotal":6154656,"ShotsFiredTotal":22512823},{"Rank":66,"ID":65193,"Username":"LoIVeR","Time":8872441,"Kills":2621,"Gems":1062,"DeathType":3,"ShotsHit":21154,"ShotsFired":66953,"TimeTotal":3798337080,"KillsTotal":1002262,"GemsTotal":239637,"DeathsTotal":2437,"ShotsHitTotal":3947979,"ShotsFiredTotal":14779597},{"Rank":67,"ID":180168,"Username":"NO STOP DONT LOVE ME","Time":8866776,"Kills":2348,"Gems":975,"DeathType":1,"ShotsHit":22253,"ShotsFired":79702,"TimeTotal":5522017919,"KillsTotal":1392910,"GemsTotal":330673,"DeathsTotal":3765,"ShotsHitTotal":5293722,"ShotsFiredTotal":21961487},{"Rank":68,"ID":22768,"Username":"Dr. Shrimps","Time":8863610,"Kills":2154,"Gems":1038,"DeathType":4,"ShotsHit":20275,"ShotsFired":63811,"TimeTotal":7348732590,"KillsTotal":1663728,"GemsTotal":511038,"DeathsTotal":3704,"ShotsHitTotal":8180244,"ShotsFiredTotal":29969734},{"Rank":69,"ID":111007,"Username":"Nito","Time":8857278,"Kills":2372,"Gems":894,"DeathType":1,"ShotsHit":21112,"ShotsFired":69890,"TimeTotal":4527501308,"KillsTotal":1166094,"GemsTotal":269542,"DeathsTotal":2910,"ShotsHitTotal":4175949,"ShotsFiredTotal":15332560},{"Rank":70,"ID":118245,"Username":"EmptyMag","Time":8852113,"Kills":2090,"Gems":963,"DeathType":6,"ShotsHit":19880,"ShotsFired":62905,"TimeTotal":4473368107,"KillsTotal":923172,"GemsTotal":299826,"DeathsTotal":2632,"ShotsHitTotal":4542692,"ShotsFiredTotal":17139846},{"Rank":71,"ID":170654,"Username":"iEpicFreak","Time":8822620,"Kills":2239,"Gems":946,"DeathType":1,"ShotsHit":21205,"ShotsFired":68588,"TimeTotal":2465594177,"KillsTotal":556885,"GemsTotal":160488,"DeathsTotal":1285,"ShotsHitTotal":2633756,"ShotsFiredTotal":9938570},{"Rank":72,"ID":137044,"Username":"Doomz","Time":8800459,"Kills":2097,"Gems":922,"DeathType":11,"ShotsHit":21146,"ShotsFired":67529,"TimeTotal":5530450174,"KillsTotal":1339084,"GemsTotal":362319,"DeathsTotal":2882,"ShotsHitTotal":5954111,"ShotsFiredTotal":22892886},{"Rank":73,"ID":193671,"Username":"Braden","Time":8721812,"Kills":2125,"Gems":825,"DeathType":6,"ShotsHit":20737,"ShotsFired":71890,"TimeTotal":8679088569,"KillsTotal":1939514,"GemsTotal":511856,"DeathsTotal":5358,"ShotsHitTotal":7852195,"ShotsFiredTotal":32262724},{"Rank":74,"ID":161785,"Username":"Wesley","Time":8690319,"Kills":2596,"Gems":916,"DeathType":1,"ShotsHit":20965,"ShotsFired":67502,"TimeTotal":1407372938,"KillsTotal":321641,"GemsTotal":75346,"DeathsTotal":1114,"ShotsHitTotal":1101626,"ShotsFiredTotal":4148018},{"Rank":75,"ID":65560,"Username":"g_kub","Time":8660826,"Kills":2148,"Gems":959,"DeathType":2,"ShotsHit":19531,"ShotsFired":57088,"TimeTotal":16629359046,"KillsTotal":4226236,"GemsTotal":1124332,"DeathsTotal":9617,"ShotsHitTotal":16892857,"ShotsFiredTotal":58341791},{"Rank":76,"ID":122317,"Username":"ayuk","Time":8655328,"Kills":2273,"Gems":835,"DeathType":1,"ShotsHit":21503,"ShotsFired":72678,"TimeTotal":2109621923,"KillsTotal":422047,"GemsTotal":137468,"DeathsTotal":873,"ShotsHitTotal":2338823,"ShotsFiredTotal":8953800},{"Rank":77,"ID":151675,"Username":"VHS","Time":8644997,"Kills":2180,"Gems":856,"DeathType":10,"ShotsHit":20306,"ShotsFired":71218,"TimeTotal":14480615190,"KillsTotal":3418264,"GemsTotal":872165,"DeathsTotal":9793,"ShotsHitTotal":14363325,"ShotsFiredTotal":55335739},{"Rank":78,"ID":69737,"Username":"phigraz","Time":8625835,"Kills":2060,"Gems":891,"DeathType":1,"ShotsHit":19852,"ShotsFired":65935,"TimeTotal":7856755159,"KillsTotal":1749686,"GemsTotal":524604,"DeathsTotal":4026,"ShotsHitTotal":7507812,"ShotsFiredTotal":28369748},{"Rank":79,"ID":197276,"Username":"metalifestorm","Time":8620503,"Kills":2832,"Gems":846,"DeathType":5,"ShotsHit":20345,"ShotsFired":67845,"TimeTotal":6201239423,"KillsTotal":2008157,"GemsTotal":438991,"DeathsTotal":2720,"ShotsHitTotal":7776332,"ShotsFiredTotal":30032183},{"Rank":80,"ID":158257,"Username":"FunOrange","Time":8620336,"Kills":2390,"Gems":858,"DeathType":1,"ShotsHit":20906,"ShotsFired":71305,"TimeTotal":2300411233,"KillsTotal":567328,"GemsTotal":121952,"DeathsTotal":1675,"ShotsHitTotal":1814328,"ShotsFiredTotal":7187488},{"Rank":81,"ID":108148,"Username":"Whoneedspacee","Time":8604007,"Kills":2053,"Gems":922,"DeathType":10,"ShotsHit":18989,"ShotsFired":67294,"TimeTotal":1927482896,"KillsTotal":413325,"GemsTotal":121220,"DeathsTotal":951,"ShotsHitTotal":1832591,"ShotsFiredTotal":7702846},{"Rank":82,"ID":11356,"Username":"Do you like Ghostpedes?","Time":8588844,"Kills":2829,"Gems":1046,"DeathType":1,"ShotsHit":23098,"ShotsFired":74231,"TimeTotal":580697098,"KillsTotal":132670,"GemsTotal":44250,"DeathsTotal":233,"ShotsHitTotal":773967,"ShotsFiredTotal":2921283},{"Rank":83,"ID":362,"Username":"mummy napkin","Time":8524360,"Kills":2192,"Gems":939,"DeathType":6,"ShotsHit":18992,"ShotsFired":56637,"TimeTotal":1856980727,"KillsTotal":447947,"GemsTotal":158108,"DeathsTotal":674,"ShotsHitTotal":2361102,"ShotsFiredTotal":7753656},{"Rank":84,"ID":6425,"Username":"Littlebert","Time":8523027,"Kills":2211,"Gems":964,"DeathType":1,"ShotsHit":18628,"ShotsFired":62766,"TimeTotal":28932022710,"KillsTotal":7206398,"GemsTotal":1919142,"DeathsTotal":15258,"ShotsHitTotal":29633247,"ShotsFiredTotal":117102743},{"Rank":85,"ID":152515,"Username":"Louis","Time":8519861,"Kills":2072,"Gems":980,"DeathType":1,"ShotsHit":18947,"ShotsFired":58993,"TimeTotal":3117157895,"KillsTotal":739082,"GemsTotal":184698,"DeathsTotal":2144,"ShotsHitTotal":2693772,"ShotsFiredTotal":9736034},{"Rank":86,"ID":2076,"Username":"Myrmeleon","Time":8510363,"Kills":1995,"Gems":863,"DeathType":1,"ShotsHit":19266,"ShotsFired":63439,"TimeTotal":7728918620,"KillsTotal":1869701,"GemsTotal":552965,"DeathsTotal":4143,"ShotsHitTotal":8275920,"ShotsFiredTotal":29167064},{"Rank":87,"ID":3294,"Username":"aiunzovovor","Time":8483703,"Kills":2191,"Gems":868,"DeathType":5,"ShotsHit":19296,"ShotsFired":60738,"TimeTotal":7570396040,"KillsTotal":2102251,"GemsTotal":620744,"DeathsTotal":2876,"ShotsHitTotal":9721611,"ShotsFiredTotal":32774747},{"Rank":88,"ID":21059,"Username":"ThePassiveDada","Time":8451711,"Kills":1946,"Gems":868,"DeathType":6,"ShotsHit":18430,"ShotsFired":61598,"TimeTotal":5894548031,"KillsTotal":1268795,"GemsTotal":383862,"DeathsTotal":3217,"ShotsHitTotal":5443636,"ShotsFiredTotal":20872161},{"Rank":89,"ID":8561,"Username":"DanielJMus","Time":8445712,"Kills":2256,"Gems":813,"DeathType":3,"ShotsHit":18247,"ShotsFired":64773,"TimeTotal":8314216208,"KillsTotal":2071536,"GemsTotal":548564,"DeathsTotal":4747,"ShotsHitTotal":8400736,"ShotsFiredTotal":32789611},{"Rank":90,"ID":171175,"Username":"Grif","Time":8416886,"Kills":2146,"Gems":757,"DeathType":5,"ShotsHit":18639,"ShotsFired":71076,"TimeTotal":3539393109,"KillsTotal":756221,"GemsTotal":219768,"DeathsTotal":1957,"ShotsHitTotal":3183440,"ShotsFiredTotal":13695154},{"Rank":91,"ID":151734,"Username":"Harz.exe","Time":8391892,"Kills":2030,"Gems":883,"DeathType":3,"ShotsHit":18258,"ShotsFired":60418,"TimeTotal":22520494589,"KillsTotal":6088069,"GemsTotal":1434528,"DeathsTotal":13385,"ShotsHitTotal":22267508,"ShotsFiredTotal":81885941},{"Rank":92,"ID":66169,"Username":"playthis","Time":8377729,"Kills":1958,"Gems":880,"DeathType":6,"ShotsHit":18798,"ShotsFired":61522,"TimeTotal":6217046375,"KillsTotal":1487971,"GemsTotal":406734,"DeathsTotal":3802,"ShotsHitTotal":5975150,"ShotsFiredTotal":21438558},{"Rank":93,"ID":172395,"Username":"Tileä","Time":8339238,"Kills":2016,"Gems":835,"DeathType":2,"ShotsHit":17986,"ShotsFired":60288,"TimeTotal":6816385714,"KillsTotal":1631414,"GemsTotal":374370,"DeathsTotal":4730,"ShotsHitTotal":5638857,"ShotsFiredTotal":21132343},{"Rank":94,"ID":198582,"Username":"PigeonBoy","Time":8316244,"Kills":1920,"Gems":753,"DeathType":10,"ShotsHit":18590,"ShotsFired":71212,"TimeTotal":1935860993,"KillsTotal":423246,"GemsTotal":108816,"DeathsTotal":1017,"ShotsHitTotal":1835520,"ShotsFiredTotal":7782195},{"Rank":95,"ID":121754,"Username":"El Twig","Time":8246594,"Kills":1993,"Gems":795,"DeathType":11,"ShotsHit":18271,"ShotsFired":63079,"TimeTotal":3837256431,"KillsTotal":903942,"GemsTotal":249555,"DeathsTotal":2168,"ShotsHitTotal":3691157,"ShotsFiredTotal":14221771},{"Rank":96,"ID":168751,"Username":"scabble","Time":8220434,"Kills":2267,"Gems":820,"DeathType":1,"ShotsHit":17836,"ShotsFired":63116,"TimeTotal":4248676749,"KillsTotal":1144527,"GemsTotal":259196,"DeathsTotal":2688,"ShotsHitTotal":3962888,"ShotsFiredTotal":15407169},{"Rank":97,"ID":183403,"Username":"Bluemoon","Time":8203105,"Kills":2031,"Gems":859,"DeathType":0,"ShotsHit":18745,"ShotsFired":61617,"TimeTotal":4026884124,"KillsTotal":931951,"GemsTotal":278305,"DeathsTotal":1809,"ShotsHitTotal":4407204,"ShotsFiredTotal":16794401},{"Rank":98,"ID":133050,"Username":"Angrevol","Time":8179944,"Kills":1873,"Gems":791,"DeathType":0,"ShotsHit":17541,"ShotsFired":62424,"TimeTotal":6064758986,"KillsTotal":1227214,"GemsTotal":330957,"DeathsTotal":4057,"ShotsHitTotal":4606737,"ShotsFiredTotal":19661843},{"Rank":99,"ID":5838,"Username":"X-ray","Time":8174445,"Kills":2099,"Gems":774,"DeathType":2,"ShotsHit":18479,"ShotsFired":62841,"TimeTotal":11938075271,"KillsTotal":3355297,"GemsTotal":792569,"DeathsTotal":7544,"ShotsHitTotal":11934382,"ShotsFiredTotal":40147671},{"Rank":100,"ID":122258,"Username":"AndrewTheD","Time":8111294,"Kills":1924,"Gems":917,"DeathType":1,"ShotsHit":19244,"ShotsFired":67516,"TimeTotal":439591540,"KillsTotal":70958,"GemsTotal":18874,"DeathsTotal":294,"ShotsHitTotal":256557,"ShotsFiredTotal":1242502}]}