{"DateTime":"2019-12-16T00:00:25.6819134Z","Players":206181,"TimeGlobal":13956295496104,"KillsGlobal":3313370387,"GemsGlobal":434708688,"DeathsGlobal":19106611,"DaggersHitGlobal":7047610537,"DaggersFiredGlobal":31466902425,"Entries":[{"Rank":1,"Id":148788,"Username":"Bintr","Time":11143351,"Kills":4313,"Gems":1743,"DeathType":7,"DaggersHit":35640,"DaggersFired":93390,"TimeTotal":46132351577,"KillsTotal":13829980,"GemsTotal":4187005,"DeathsTotal":93394,"DaggersHitTotal":78337885,"DaggersFiredTotal":240657419},{"Rank":2,"Id":229,"Username":"Olof","Time":11129805,"Kills":4902,"Gems":1793,"DeathType":10,"DaggersHit":35874,"DaggersFired":94572,"TimeTotal":25039958762,"KillsTotal":9053713,"GemsTotal":2755823,"DeathsTotal":6814,"DaggersHitTotal":51733187,"DaggersFiredTotal":153858048},{"Rank":3,"Id":116704,"Username":"pocket","Time":11090170,"Kills":4292,"Gems":1720,"DeathType":3,"DaggersHit":34998,"DaggersFired":91207,"TimeTotal":11904818444,"KillsTotal":4290928,"GemsTotal":1234898,"DeathsTotal":3786,"DaggersHitTotal":22998961,"DaggersFiredTotal":68167726},{"Rank":4,"Id":118832,"Username":"Chupacabra","Time":11078129,"Kills":4111,"Gems":1655,"DeathType":5,"DaggersHit":34733,"DaggersFired":92124,"TimeTotal":20259616747,"KillsTotal":6342692,"GemsTotal":2076763,"DeathsTotal":6079,"DaggersHitTotal":40397260,"DaggersFiredTotal":121795810},{"Rank":5,"Id":1545,"Username":"KrosisOne","Time":11055385,"Kills":4064,"Gems":1610,"DeathType":12,"DaggersHit":34844,"DaggersFired":95511,"TimeTotal":54305116607,"KillsTotal":16634315,"GemsTotal":5229373,"DeathsTotal":17044,"DaggersHitTotal":97970679,"DaggersFiredTotal":308146887},{"Rank":6,"Id":93991,"Username":"cookle","Time":10983640,"Kills":4243,"Gems":1699,"DeathType":1,"DaggersHit":34005,"DaggersFired":93123,"TimeTotal":17712945232,"KillsTotal":5064819,"GemsTotal":1528530,"DeathsTotal":9619,"DaggersHitTotal":26579809,"DaggersFiredTotal":83533369},{"Rank":7,"Id":86805,"Username":"Ravenholmzombies","Time":10951364,"Kills":3985,"Gems":1659,"DeathType":10,"DaggersHit":34169,"DaggersFired":95637,"TimeTotal":19309867876,"KillsTotal":5481392,"GemsTotal":1679734,"DeathsTotal":6748,"DaggersHitTotal":30040111,"DaggersFiredTotal":106145726},{"Rank":8,"Id":1135,"Username":"bowsr","Time":10803359,"Kills":4099,"Gems":1602,"DeathType":5,"DaggersHit":33341,"DaggersFired":88113,"TimeTotal":15760336525,"KillsTotal":5410939,"GemsTotal":1623269,"DeathsTotal":5106,"DaggersHitTotal":29746918,"DaggersFiredTotal":85650923},{"Rank":9,"Id":134802,"Username":"gLad","Time":10797339,"Kills":4049,"Gems":1628,"DeathType":1,"DaggersHit":33442,"DaggersFired":91476,"TimeTotal":22736018730,"KillsTotal":7235780,"GemsTotal":2086453,"DeathsTotal":7800,"DaggersHitTotal":37490689,"DaggersFiredTotal":119362422},{"Rank":10,"Id":1677,"Username":"ᴧ и т.⁴","Time":10735461,"Kills":3992,"Gems":1475,"DeathType":5,"DaggersHit":31801,"DaggersFired":87803,"TimeTotal":16309516001,"KillsTotal":5328582,"GemsTotal":1578291,"DeathsTotal":4808,"DaggersHitTotal":29475652,"DaggersFiredTotal":91372626},{"Rank":11,"Id":21854,"Username":"xvlv","Time":10630103,"Kills":3801,"Gems":1446,"DeathType":7,"DaggersHit":31233,"DaggersFired":86913,"TimeTotal":20227718895,"KillsTotal":5464737,"GemsTotal":1914845,"DeathsTotal":5570,"DaggersHitTotal":37377543,"DaggersFiredTotal":124132255},{"Rank":12,"Id":173419,"Username":"Kasa","Time":10628096,"Kills":3533,"Gems":1474,"DeathType":5,"DaggersHit":32335,"DaggersFired":90458,"TimeTotal":10506970026,"KillsTotal":2905395,"GemsTotal":962631,"DeathsTotal":3402,"DaggersHitTotal":18235915,"DaggersFiredTotal":60025417},{"Rank":13,"Id":6760,"Username":"TSTAB","Time":10585952,"Kills":3948,"Gems":1485,"DeathType":6,"DaggersHit":32015,"DaggersFired":92241,"TimeTotal":21482744459,"KillsTotal":6354561,"GemsTotal":1699897,"DeathsTotal":9125,"DaggersHitTotal":29231291,"DaggersFiredTotal":99186828},{"Rank":14,"Id":153452,"Username":"tacocat","Time":10584949,"Kills":3855,"Gems":1486,"DeathType":3,"DaggersHit":31539,"DaggersFired":91301,"TimeTotal":17739243296,"KillsTotal":5232743,"GemsTotal":1379275,"DeathsTotal":8925,"DaggersHitTotal":22890121,"DaggersFiredTotal":78752340},{"Rank":15,"Id":106722,"Username":"pocket","Time":10530931,"Kills":4132,"Gems":1592,"DeathType":11,"DaggersHit":32846,"DaggersFired":83968,"TimeTotal":21036080111,"KillsTotal":6670024,"GemsTotal":1734347,"DeathsTotal":10263,"DaggersHitTotal":29680337,"DaggersFiredTotal":94127210},{"Rank":16,"Id":182924,"Username":"axe","Time":10474238,"Kills":3711,"Gems":1401,"DeathType":5,"DaggersHit":30967,"DaggersFired":92602,"TimeTotal":13764942201,"KillsTotal":3929789,"GemsTotal":1042818,"DeathsTotal":6503,"DaggersHitTotal":18778450,"DaggersFiredTotal":66311680},{"Rank":17,"Id":10210,"Username":"sjorsbw","Time":10398480,"Kills":3035,"Gems":1463,"DeathType":3,"DaggersHit":29478,"DaggersFired":86834,"TimeTotal":14872735603,"KillsTotal":3566923,"GemsTotal":1251103,"DeathsTotal":6981,"DaggersHitTotal":21662408,"DaggersFiredTotal":76828279},{"Rank":18,"Id":105874,"Username":"Dkazyo","Time":10283254,"Kills":3266,"Gems":1449,"DeathType":10,"DaggersHit":29333,"DaggersFired":80296,"TimeTotal":11429315474,"KillsTotal":2994107,"GemsTotal":1007327,"DeathsTotal":4433,"DaggersHitTotal":17495529,"DaggersFiredTotal":58430493},{"Rank":19,"Id":5757,"Username":"Cobajj","Time":10274391,"Kills":3334,"Gems":1381,"DeathType":2,"DaggersHit":29430,"DaggersFired":83761,"TimeTotal":18128091522,"KillsTotal":4684262,"GemsTotal":1296396,"DeathsTotal":9661,"DaggersHitTotal":20219935,"DaggersFiredTotal":75444692},{"Rank":20,"Id":18469,"Username":"trauma queen","Time":10264189,"Kills":3402,"Gems":1304,"DeathType":1,"DaggersHit":29446,"DaggersFired":85429,"TimeTotal":7106046634,"KillsTotal":1953657,"GemsTotal":550799,"DeathsTotal":3264,"DaggersHitTotal":9167084,"DaggersFiredTotal":29737482},{"Rank":21,"Id":115431,"Username":"Pritster","Time":10258002,"Kills":2949,"Gems":1264,"DeathType":10,"DaggersHit":28571,"DaggersFired":91164,"TimeTotal":43534573121,"KillsTotal":10500612,"GemsTotal":3755486,"DeathsTotal":13264,"DaggersHitTotal":70078194,"DaggersFiredTotal":252837638},{"Rank":22,"Id":121891,"Username":"xamide","Time":10249473,"Kills":3328,"Gems":1338,"DeathType":1,"DaggersHit":29438,"DaggersFired":89015,"TimeTotal":10043679509,"KillsTotal":3036845,"GemsTotal":795042,"DeathsTotal":4584,"DaggersHitTotal":13397473,"DaggersFiredTotal":46725690},{"Rank":23,"Id":148130,"Username":"BLANK_END","Time":10245626,"Kills":3085,"Gems":1252,"DeathType":10,"DaggersHit":29336,"DaggersFired":87995,"TimeTotal":7421569257,"KillsTotal":1929285,"GemsTotal":534358,"DeathsTotal":3806,"DaggersHitTotal":9976812,"DaggersFiredTotal":34757292},{"Rank":24,"Id":438,"Username":"Kaijt","Time":10179955,"Kills":2961,"Gems":1332,"DeathType":11,"DaggersHit":27866,"DaggersFired":80010,"TimeTotal":7456412450,"KillsTotal":2071737,"GemsTotal":647833,"DeathsTotal":2693,"DaggersHitTotal":10838142,"DaggersFiredTotal":35775751},{"Rank":25,"Id":48687,"Username":"Hahmo","Time":10176290,"Kills":3483,"Gems":1398,"DeathType":1,"DaggersHit":28476,"DaggersFired":83350,"TimeTotal":12216021140,"KillsTotal":3228549,"GemsTotal":972891,"DeathsTotal":5174,"DaggersHitTotal":16458219,"DaggersFiredTotal":58044598},{"Rank":26,"Id":106181,"Username":"flubb","Time":10123136,"Kills":3285,"Gems":1313,"DeathType":11,"DaggersHit":27810,"DaggersFired":79796,"TimeTotal":14432891988,"KillsTotal":3724196,"GemsTotal":1025039,"DeathsTotal":9358,"DaggersHitTotal":16380113,"DaggersFiredTotal":55772030},{"Rank":27,"Id":188777,"Username":"_whipsta","Time":10119470,"Kills":3615,"Gems":1330,"DeathType":1,"DaggersHit":29291,"DaggersFired":91035,"TimeTotal":15278467748,"KillsTotal":4637002,"GemsTotal":1141847,"DeathsTotal":7861,"DaggersHitTotal":18015926,"DaggersFiredTotal":63861384},{"Rank":28,"Id":148518,"Username":"oi fuck head","Time":10112639,"Kills":2694,"Gems":1259,"DeathType":2,"DaggersHit":26830,"DaggersFired":84535,"TimeTotal":6499854913,"KillsTotal":1038891,"GemsTotal":347292,"DeathsTotal":60801,"DaggersHitTotal":6298490,"DaggersFiredTotal":21356139},{"Rank":29,"Id":65617,"Username":"pagedMov","Time":10106807,"Kills":2934,"Gems":1255,"DeathType":3,"DaggersHit":27867,"DaggersFired":89517,"TimeTotal":15022871312,"KillsTotal":3684148,"GemsTotal":1237916,"DeathsTotal":6556,"DaggersHitTotal":20859599,"DaggersFiredTotal":69365948},{"Rank":30,"Id":142939,"Username":"LocoCaesar_IV","Time":10100808,"Kills":3279,"Gems":1272,"DeathType":3,"DaggersHit":28364,"DaggersFired":87045,"TimeTotal":30955969481,"KillsTotal":8023998,"GemsTotal":2368668,"DeathsTotal":16486,"DaggersHitTotal":39686941,"DaggersFiredTotal":132036488},{"Rank":31,"Id":10782,"Username":"Nullifier","Time":10039823,"Kills":3068,"Gems":1290,"DeathType":11,"DaggersHit":27930,"DaggersFired":85804,"TimeTotal":15210692880,"KillsTotal":4283650,"GemsTotal":1028869,"DeathsTotal":8891,"DaggersHitTotal":15905346,"DaggersFiredTotal":56733090},{"Rank":32,"Id":112710,"Username":"7stringTheory","Time":10038490,"Kills":2990,"Gems":1288,"DeathType":1,"DaggersHit":27207,"DaggersFired":85967,"TimeTotal":21858633826,"KillsTotal":5973244,"GemsTotal":1621364,"DeathsTotal":10087,"DaggersHitTotal":26666393,"DaggersFiredTotal":99024348},{"Rank":33,"Id":105641,"Username":"jay","Time":10029825,"Kills":3405,"Gems":1314,"DeathType":4,"DaggersHit":27752,"DaggersFired":85259,"TimeTotal":10029737059,"KillsTotal":3010170,"GemsTotal":722663,"DeathsTotal":6025,"DaggersHitTotal":11732494,"DaggersFiredTotal":38074998},{"Rank":34,"Id":184178,"Username":"Mizore <3","Time":9922852,"Kills":3051,"Gems":1255,"DeathType":1,"DaggersHit":27310,"DaggersFired":84561,"TimeTotal":1787638854,"KillsTotal":585371,"GemsTotal":151192,"DeathsTotal":773,"DaggersHitTotal":2659127,"DaggersFiredTotal":9215135},{"Rank":35,"Id":19658,"Username":"krak~☆","Time":9864366,"Kills":2796,"Gems":1333,"DeathType":1,"DaggersHit":27579,"DaggersFired":80022,"TimeTotal":16237790671,"KillsTotal":4084647,"GemsTotal":1178891,"DeathsTotal":8260,"DaggersHitTotal":19173110,"DaggersFiredTotal":64769733},{"Rank":36,"Id":157181,"Username":"PS3 controller","Time":9837372,"Kills":3188,"Gems":1239,"DeathType":10,"DaggersHit":26816,"DaggersFired":83105,"TimeTotal":834477435,"KillsTotal":190476,"GemsTotal":52191,"DeathsTotal":314,"DaggersHitTotal":897858,"DaggersFiredTotal":3142588},{"Rank":37,"Id":2316,"Username":"aircawn","Time":9793883,"Kills":3034,"Gems":1212,"DeathType":10,"DaggersHit":25393,"DaggersFired":72143,"TimeTotal":14381961584,"KillsTotal":3894645,"GemsTotal":1246794,"DeathsTotal":4805,"DaggersHitTotal":21058959,"DaggersFiredTotal":67719531},{"Rank":38,"Id":90050,"Username":"Impressive","Time":9688742,"Kills":3007,"Gems":1196,"DeathType":1,"DaggersHit":25529,"DaggersFired":77606,"TimeTotal":21354035824,"KillsTotal":5424369,"GemsTotal":1403669,"DeathsTotal":13204,"DaggersHitTotal":21022217,"DaggersFiredTotal":73633856},{"Rank":39,"Id":10045,"Username":"Blue53","Time":9578102,"Kills":2859,"Gems":1120,"DeathType":15,"DaggersHit":25290,"DaggersFired":74064,"TimeTotal":15254194283,"KillsTotal":4063096,"GemsTotal":1058277,"DeathsTotal":8219,"DaggersHitTotal":17378111,"DaggersFiredTotal":59223009},{"Rank":40,"Id":175805,"Username":"Enough","Time":9545277,"Kills":3094,"Gems":1225,"DeathType":3,"DaggersHit":25635,"DaggersFired":74074,"TimeTotal":7443062061,"KillsTotal":2133805,"GemsTotal":563780,"DeathsTotal":3762,"DaggersHitTotal":9109469,"DaggersFiredTotal":30073132},{"Rank":41,"Id":177725,"Username":"Deunousen","Time":9498455,"Kills":2957,"Gems":1126,"DeathType":1,"DaggersHit":25097,"DaggersFired":75552,"TimeTotal":5359628472,"KillsTotal":1509477,"GemsTotal":384177,"DeathsTotal":2482,"DaggersHitTotal":6080440,"DaggersFiredTotal":20986216},{"Rank":42,"Id":81895,"Username":"zealotsthename † 狂热者","Time":9420974,"Kills":2677,"Gems":1096,"DeathType":6,"DaggersHit":23925,"DaggersFired":76689,"TimeTotal":13563873925,"KillsTotal":3445812,"GemsTotal":981793,"DeathsTotal":6980,"DaggersHitTotal":15663563,"DaggersFiredTotal":58769902},{"Rank":43,"Id":166973,"Username":"[G]rizz","Time":9397480,"Kills":2554,"Gems":1139,"DeathType":12,"DaggersHit":23792,"DaggersFired":75562,"TimeTotal":7959582972,"KillsTotal":2359227,"GemsTotal":522370,"DeathsTotal":4907,"DaggersHitTotal":8878950,"DaggersFiredTotal":33446429},{"Rank":44,"Id":146931,"Username":"Duncdaddi","Time":9340494,"Kills":2539,"Gems":986,"DeathType":4,"DaggersHit":23646,"DaggersFired":71132,"TimeTotal":7535319067,"KillsTotal":1706958,"GemsTotal":477877,"DeathsTotal":4392,"DaggersHitTotal":7670521,"DaggersFiredTotal":29071826},{"Rank":45,"Id":152889,"Username":"Puhree","Time":9335828,"Kills":2921,"Gems":1166,"DeathType":5,"DaggersHit":23925,"DaggersFired":73513,"TimeTotal":12529299838,"KillsTotal":3303432,"GemsTotal":862039,"DeathsTotal":6438,"DaggersHitTotal":13980001,"DaggersFiredTotal":50409899},{"Rank":46,"Id":105315,"Username":"LukeNukem","Time":9288840,"Kills":2821,"Gems":1049,"DeathType":12,"DaggersHit":23568,"DaggersFired":72729,"TimeTotal":22663783964,"KillsTotal":6912015,"GemsTotal":1451676,"DeathsTotal":14252,"DaggersHitTotal":22241904,"DaggersFiredTotal":76444803},{"Rank":47,"Id":58654,"Username":"CCT","Time":9230021,"Kills":2492,"Gems":1010,"DeathType":11,"DaggersHit":22890,"DaggersFired":76845,"TimeTotal":10191285887,"KillsTotal":2651234,"GemsTotal":762364,"DeathsTotal":3793,"DaggersHitTotal":13742772,"DaggersFiredTotal":52371438},{"Rank":48,"Id":176615,"Username":"Hostolonius","Time":9228854,"Kills":2330,"Gems":984,"DeathType":10,"DaggersHit":23300,"DaggersFired":79489,"TimeTotal":9042400867,"KillsTotal":1989543,"GemsTotal":641374,"DeathsTotal":4613,"DaggersHitTotal":10989911,"DaggersFiredTotal":41673028},{"Rank":49,"Id":112879,"Username":"_","Time":9176534,"Kills":3414,"Gems":1086,"DeathType":6,"DaggersHit":24407,"DaggersFired":79510,"TimeTotal":11971291953,"KillsTotal":4042318,"GemsTotal":701644,"DeathsTotal":11407,"DaggersHitTotal":10585203,"DaggersFiredTotal":35763865},{"Rank":50,"Id":82980,"Username":"Emberstone","Time":9172368,"Kills":2345,"Gems":1072,"DeathType":15,"DaggersHit":22147,"DaggersFired":63542,"TimeTotal":8671932336,"KillsTotal":2009527,"GemsTotal":614028,"DeathsTotal":4394,"DaggersHitTotal":9129241,"DaggersFiredTotal":31777506},{"Rank":51,"Id":148538,"Username":"paxtank","Time":9153706,"Kills":2461,"Gems":988,"DeathType":1,"DaggersHit":23007,"DaggersFired":70936,"TimeTotal":11877938161,"KillsTotal":3035504,"GemsTotal":740993,"DeathsTotal":8457,"DaggersHitTotal":11476329,"DaggersFiredTotal":39995146},{"Rank":52,"Id":166941,"Username":"iNooVa","Time":9149041,"Kills":2440,"Gems":889,"DeathType":3,"DaggersHit":23070,"DaggersFired":80412,"TimeTotal":2532403693,"KillsTotal":552032,"GemsTotal":163346,"DeathsTotal":1384,"DaggersHitTotal":2682661,"DaggersFiredTotal":10566988},{"Rank":53,"Id":4795,"Username":"Moz","Time":9129379,"Kills":2432,"Gems":1099,"DeathType":2,"DaggersHit":21908,"DaggersFired":68755,"TimeTotal":10249983289,"KillsTotal":2541187,"GemsTotal":854711,"DeathsTotal":3616,"DaggersHitTotal":13688635,"DaggersFiredTotal":49129693},{"Rank":54,"Id":94857,"Username":"Birder brain player","Time":9094720,"Kills":2231,"Gems":1061,"DeathType":3,"DaggersHit":22632,"DaggersFired":67990,"TimeTotal":4977881520,"KillsTotal":1091900,"GemsTotal":336329,"DeathsTotal":2597,"DaggersHitTotal":4846502,"DaggersFiredTotal":17623167},{"Rank":55,"Id":27510,"Username":"Billy the Butcher","Time":9058396,"Kills":2428,"Gems":986,"DeathType":3,"DaggersHit":21924,"DaggersFired":66412,"TimeTotal":8061114810,"KillsTotal":1900988,"GemsTotal":548829,"DeathsTotal":4573,"DaggersHitTotal":8534432,"DaggersFiredTotal":30008968},{"Rank":56,"Id":1029,"Username":"ohsnaplol","Time":9054897,"Kills":2419,"Gems":999,"DeathType":10,"DaggersHit":21331,"DaggersFired":64581,"TimeTotal":6238024601,"KillsTotal":1597295,"GemsTotal":445808,"DeathsTotal":2972,"DaggersHitTotal":7024766,"DaggersFiredTotal":24282277},{"Rank":57,"Id":157108,"Username":"Jyff","Time":9032736,"Kills":3091,"Gems":1090,"DeathType":1,"DaggersHit":23325,"DaggersFired":66953,"TimeTotal":21748876308,"KillsTotal":7577930,"GemsTotal":1466684,"DeathsTotal":12975,"DaggersHitTotal":24007075,"DaggersFiredTotal":82328068},{"Rank":58,"Id":193297,"Username":"Driftkon","Time":8998911,"Kills":2000,"Gems":811,"DeathType":5,"DaggersHit":21010,"DaggersFired":72885,"TimeTotal":4542400620,"KillsTotal":882409,"GemsTotal":263779,"DeathsTotal":2382,"DaggersHitTotal":3958937,"DaggersFiredTotal":16719875},{"Rank":59,"Id":89987,"Username":"Goobermin","Time":8988913,"Kills":2693,"Gems":808,"DeathType":7,"DaggersHit":23010,"DaggersFired":79381,"TimeTotal":13161546239,"KillsTotal":3936265,"GemsTotal":767677,"DeathsTotal":8900,"DaggersHitTotal":12860230,"DaggersFiredTotal":44810304},{"Rank":60,"Id":75575,"Username":"p0cket","Time":8978749,"Kills":2630,"Gems":1122,"DeathType":1,"DaggersHit":23616,"DaggersFired":67099,"TimeTotal":24928835484,"KillsTotal":6165566,"GemsTotal":2063038,"DeathsTotal":10627,"DaggersHitTotal":35339707,"DaggersFiredTotal":118401471},{"Rank":61,"Id":71157,"Username":"Chopps The Penguin","Time":8935259,"Kills":2701,"Gems":995,"DeathType":11,"DaggersHit":22265,"DaggersFired":73096,"TimeTotal":8285031331,"KillsTotal":2321729,"GemsTotal":491653,"DeathsTotal":5563,"DaggersHitTotal":7810288,"DaggersFiredTotal":28931586},{"Rank":62,"Id":113530,"Username":"Zirtonic","Time":8924262,"Kills":2361,"Gems":992,"DeathType":2,"DaggersHit":22072,"DaggersFired":69751,"TimeTotal":4970118360,"KillsTotal":1136666,"GemsTotal":353424,"DeathsTotal":2202,"DaggersHitTotal":5367943,"DaggersFiredTotal":18685063},{"Rank":63,"Id":531,"Username":"GaryBanderas","Time":8924095,"Kills":2154,"Gems":1041,"DeathType":10,"DaggersHit":21362,"DaggersFired":64588,"TimeTotal":21198233183,"KillsTotal":4650081,"GemsTotal":1611462,"DeathsTotal":8378,"DaggersHitTotal":26078918,"DaggersFiredTotal":99296017},{"Rank":64,"Id":168681,"Username":"azuki","Time":8880606,"Kills":2261,"Gems":1029,"DeathType":3,"DaggersHit":21081,"DaggersFired":67661,"TimeTotal":6766319065,"KillsTotal":1852722,"GemsTotal":403218,"DeathsTotal":4538,"DaggersHitTotal":6154656,"DaggersFiredTotal":22512823},{"Rank":65,"Id":65193,"Username":"LoIVeR","Time":8872441,"Kills":2621,"Gems":1062,"DeathType":3,"DaggersHit":21154,"DaggersFired":66953,"TimeTotal":3748072892,"KillsTotal":988120,"GemsTotal":236183,"DeathsTotal":2409,"DaggersHitTotal":3889831,"DaggersFiredTotal":14578355},{"Rank":66,"Id":180168,"Username":"cooomer","Time":8866776,"Kills":2348,"Gems":975,"DeathType":1,"DaggersHit":22253,"DaggersFired":79702,"TimeTotal":5451725905,"KillsTotal":1374085,"GemsTotal":325473,"DeathsTotal":3728,"DaggersHitTotal":5204339,"DaggersFiredTotal":21612019},{"Rank":67,"Id":22768,"Username":"Dr. Shrimps","Time":8863610,"Kills":2154,"Gems":1038,"DeathType":4,"DaggersHit":20275,"DaggersFired":63811,"TimeTotal":7342268541,"KillsTotal":1661613,"GemsTotal":510226,"DeathsTotal":3700,"DaggersHitTotal":8167202,"DaggersFiredTotal":29918450},{"Rank":68,"Id":111007,"Username":"goodluckNito.ttv","Time":8857278,"Kills":2372,"Gems":894,"DeathType":1,"DaggersHit":21112,"DaggersFired":69890,"TimeTotal":4126521168,"KillsTotal":1051937,"GemsTotal":240609,"DeathsTotal":2701,"DaggersHitTotal":3725825,"DaggersFiredTotal":13782331},{"Rank":69,"Id":118245,"Username":"EmptyMag","Time":8852113,"Kills":2090,"Gems":963,"DeathType":6,"DaggersHit":19880,"DaggersFired":62905,"TimeTotal":4467603466,"KillsTotal":921820,"GemsTotal":299421,"DeathsTotal":2630,"DaggersHitTotal":4537449,"DaggersFiredTotal":17120121},{"Rank":70,"Id":170654,"Username":"iEpicFreak","Time":8822620,"Kills":2239,"Gems":946,"DeathType":1,"DaggersHit":21205,"DaggersFired":68588,"TimeTotal":2460973257,"KillsTotal":555541,"GemsTotal":160185,"DeathsTotal":1283,"DaggersHitTotal":2629705,"DaggersFiredTotal":9922909},{"Rank":71,"Id":137044,"Username":"Doomz","Time":8800459,"Kills":2097,"Gems":922,"DeathType":11,"DaggersHit":21146,"DaggersFired":67529,"TimeTotal":5515940063,"KillsTotal":1335846,"GemsTotal":361217,"DeathsTotal":2877,"DaggersHitTotal":5937865,"DaggersFiredTotal":22835889},{"Rank":72,"Id":40892,"Username":"Bruh","Time":8757469,"Kills":2139,"Gems":835,"DeathType":6,"DaggersHit":20614,"DaggersFired":73531,"TimeTotal":7807653520,"KillsTotal":1584220,"GemsTotal":488484,"DeathsTotal":3976,"DaggersHitTotal":7452010,"DaggersFiredTotal":29760582},{"Rank":73,"Id":193671,"Username":"Braden","Time":8721812,"Kills":2125,"Gems":825,"DeathType":6,"DaggersHit":20737,"DaggersFired":71890,"TimeTotal":8446184678,"KillsTotal":1881824,"GemsTotal":494182,"DeathsTotal":5257,"DaggersHitTotal":7567583,"DaggersFiredTotal":31148587},{"Rank":74,"Id":161785,"Username":"Wesley","Time":8690319,"Kills":2596,"Gems":916,"DeathType":1,"DaggersHit":20965,"DaggersFired":67502,"TimeTotal":1407372938,"KillsTotal":321641,"GemsTotal":75346,"DeathsTotal":1114,"DaggersHitTotal":1101626,"DaggersFiredTotal":4148018},{"Rank":75,"Id":65560,"Username":"g_kub","Time":8660826,"Kills":2148,"Gems":959,"DeathType":2,"DaggersHit":19531,"DaggersFired":57088,"TimeTotal":16629359046,"KillsTotal":4226236,"GemsTotal":1124332,"DeathsTotal":9617,"DaggersHitTotal":16892857,"DaggersFiredTotal":58341791},{"Rank":76,"Id":122317,"Username":"ayuk","Time":8655328,"Kills":2273,"Gems":835,"DeathType":1,"DaggersHit":21503,"DaggersFired":72678,"TimeTotal":2109621923,"KillsTotal":422047,"GemsTotal":137468,"DeathsTotal":873,"DaggersHitTotal":2338823,"DaggersFiredTotal":8953800},{"Rank":77,"Id":151675,"Username":"VHS","Time":8644997,"Kills":2180,"Gems":856,"DeathType":10,"DaggersHit":20306,"DaggersFired":71218,"TimeTotal":14475266020,"KillsTotal":3416765,"GemsTotal":871663,"DeathsTotal":9746,"DaggersHitTotal":14356849,"DaggersFiredTotal":55308097},{"Rank":78,"Id":69737,"Username":"ancient_geometrist","Time":8625835,"Kills":2060,"Gems":891,"DeathType":1,"DaggersHit":19852,"DaggersFired":65935,"TimeTotal":7854669561,"KillsTotal":1749148,"GemsTotal":524473,"DeathsTotal":4025,"DaggersHitTotal":7506369,"DaggersFiredTotal":28363598},{"Rank":79,"Id":158257,"Username":"FunOrange","Time":8620336,"Kills":2390,"Gems":858,"DeathType":1,"DaggersHit":20906,"DaggersFired":71305,"TimeTotal":2300411233,"KillsTotal":567328,"GemsTotal":121952,"DeathsTotal":1675,"DaggersHitTotal":1814328,"DaggersFiredTotal":7187488},{"Rank":80,"Id":108148,"Username":"Whoneedspacee","Time":8604007,"Kills":2053,"Gems":922,"DeathType":10,"DaggersHit":18989,"DaggersFired":67294,"TimeTotal":1927482896,"KillsTotal":413325,"GemsTotal":121220,"DeathsTotal":951,"DaggersHitTotal":1832591,"DaggersFiredTotal":7702846},{"Rank":81,"Id":11356,"Username":"Do you like Ghostpedes?","Time":8588844,"Kills":2829,"Gems":1046,"DeathType":1,"DaggersHit":23098,"DaggersFired":74231,"TimeTotal":580697098,"KillsTotal":132670,"GemsTotal":44250,"DeathsTotal":233,"DaggersHitTotal":773967,"DaggersFiredTotal":2921283},{"Rank":82,"Id":362,"Username":"mummy napkin","Time":8524360,"Kills":2192,"Gems":939,"DeathType":6,"DaggersHit":18992,"DaggersFired":56637,"TimeTotal":1856980727,"KillsTotal":447947,"GemsTotal":158108,"DeathsTotal":674,"DaggersHitTotal":2361102,"DaggersFiredTotal":7753656},{"Rank":83,"Id":6425,"Username":"Littlebert","Time":8523027,"Kills":2211,"Gems":964,"DeathType":1,"DaggersHit":18628,"DaggersFired":62766,"TimeTotal":28932022710,"KillsTotal":7206398,"GemsTotal":1919142,"DeathsTotal":15258,"DaggersHitTotal":29633247,"DaggersFiredTotal":117102743},{"Rank":84,"Id":2076,"Username":"Myrmeleon","Time":8510363,"Kills":1995,"Gems":863,"DeathType":1,"DaggersHit":19266,"DaggersFired":63439,"TimeTotal":7728918620,"KillsTotal":1869701,"GemsTotal":552965,"DeathsTotal":4143,"DaggersHitTotal":8275920,"DaggersFiredTotal":29167064},{"Rank":85,"Id":3294,"Username":"aiunzovovor","Time":8483703,"Kills":2191,"Gems":868,"DeathType":5,"DaggersHit":19296,"DaggersFired":60738,"TimeTotal":7570396040,"KillsTotal":2102251,"GemsTotal":620744,"DeathsTotal":2876,"DaggersHitTotal":9721611,"DaggersFiredTotal":32774747},{"Rank":86,"Id":21059,"Username":"ThePassiveDada","Time":8451711,"Kills":1946,"Gems":868,"DeathType":6,"DaggersHit":18430,"DaggersFired":61598,"TimeTotal":5894548031,"KillsTotal":1268795,"GemsTotal":383862,"DeathsTotal":3217,"DaggersHitTotal":5443636,"DaggersFiredTotal":20872161},{"Rank":87,"Id":8561,"Username":"DanielJMus","Time":8445712,"Kills":2256,"Gems":813,"DeathType":3,"DaggersHit":18247,"DaggersFired":64773,"TimeTotal":8314216208,"KillsTotal":2071536,"GemsTotal":548564,"DeathsTotal":4747,"DaggersHitTotal":8400736,"DaggersFiredTotal":32789611},{"Rank":88,"Id":171175,"Username":"Grif","Time":8416886,"Kills":2146,"Gems":757,"DeathType":5,"DaggersHit":18639,"DaggersFired":71076,"TimeTotal":3536553625,"KillsTotal":755375,"GemsTotal":219668,"DeathsTotal":1954,"DaggersHitTotal":3181755,"DaggersFiredTotal":13689121},{"Rank":89,"Id":151734,"Username":"Harz.exe","Time":8391892,"Kills":2030,"Gems":883,"DeathType":3,"DaggersHit":18258,"DaggersFired":60418,"TimeTotal":22408658276,"KillsTotal":6059101,"GemsTotal":1424828,"DeathsTotal":13343,"DaggersHitTotal":22102245,"DaggersFiredTotal":81331883},{"Rank":90,"Id":66169,"Username":"playthis","Time":8377729,"Kills":1958,"Gems":880,"DeathType":6,"DaggersHit":18798,"DaggersFired":61522,"TimeTotal":6217046375,"KillsTotal":1487971,"GemsTotal":406734,"DeathsTotal":3802,"DaggersHitTotal":5975150,"DaggersFiredTotal":21438558},{"Rank":91,"Id":172395,"Username":"Tileä","Time":8339238,"Kills":2016,"Gems":835,"DeathType":2,"DaggersHit":17986,"DaggersFired":60288,"TimeTotal":6816385714,"KillsTotal":1631414,"GemsTotal":374370,"DeathsTotal":4730,"DaggersHitTotal":5638857,"DaggersFiredTotal":21132343},{"Rank":92,"Id":198582,"Username":"PigeonBoy","Time":8316244,"Kills":1920,"Gems":753,"DeathType":10,"DaggersHit":18590,"DaggersFired":71212,"TimeTotal":1935860993,"KillsTotal":423246,"GemsTotal":108816,"DeathsTotal":1017,"DaggersHitTotal":1835520,"DaggersFiredTotal":7782195},{"Rank":93,"Id":121754,"Username":"El Twig","Time":8246594,"Kills":1993,"Gems":795,"DeathType":11,"DaggersHit":18271,"DaggersFired":63079,"TimeTotal":3837256431,"KillsTotal":903942,"GemsTotal":249555,"DeathsTotal":2168,"DaggersHitTotal":3691157,"DaggersFiredTotal":14221771},{"Rank":94,"Id":168751,"Username":"scabble","Time":8220434,"Kills":2267,"Gems":820,"DeathType":1,"DaggersHit":17836,"DaggersFired":63116,"TimeTotal":4221881242,"KillsTotal":1136424,"GemsTotal":257453,"DeathsTotal":2672,"DaggersHitTotal":3936010,"DaggersFiredTotal":15312194},{"Rank":95,"Id":183403,"Username":"Bluemoon","Time":8203105,"Kills":2031,"Gems":859,"DeathType":0,"DaggersHit":18745,"DaggersFired":61617,"TimeTotal":4026884124,"KillsTotal":931951,"GemsTotal":278305,"DeathsTotal":1809,"DaggersHitTotal":4407204,"DaggersFiredTotal":16794401},{"Rank":96,"Id":133050,"Username":"Angrevol","Time":8179944,"Kills":1873,"Gems":791,"DeathType":0,"DaggersHit":17541,"DaggersFired":62424,"TimeTotal":6060655028,"KillsTotal":1226544,"GemsTotal":330641,"DeathsTotal":4055,"DaggersHitTotal":4601220,"DaggersFiredTotal":19641154},{"Rank":97,"Id":5838,"Username":"X-ray","Time":8174445,"Kills":2099,"Gems":774,"DeathType":2,"DaggersHit":18479,"DaggersFired":62841,"TimeTotal":11938075271,"KillsTotal":3355297,"GemsTotal":792569,"DeathsTotal":7544,"DaggersHitTotal":11934382,"DaggersFiredTotal":40147671},{"Rank":98,"Id":122258,"Username":"AndrewTheD","Time":8111294,"Kills":1924,"Gems":917,"DeathType":1,"DaggersHit":19244,"DaggersFired":67516,"TimeTotal":439591540,"KillsTotal":70958,"GemsTotal":18874,"DeathsTotal":294,"DaggersHitTotal":256557,"DaggersFiredTotal":1242502},{"Rank":99,"Id":117558,"Username":"bob from food use","Time":8085800,"Kills":2076,"Gems":885,"DeathType":1,"DaggersHit":16813,"DaggersFired":58528,"TimeTotal":100749996,"KillsTotal":25609,"GemsTotal":8927,"DeathsTotal":33,"DaggersHitTotal":149965,"DaggersFiredTotal":529261},{"Rank":100,"Id":68151,"Username":"Faad3e_","Time":7971328,"Kills":1803,"Gems":785,"DeathType":15,"DaggersHit":17331,"DaggersFired":63502,"TimeTotal":2843434332,"KillsTotal":689413,"GemsTotal":183400,"DeathsTotal":1459,"DaggersHitTotal":2819023,"DaggersFiredTotal":11746906}]}